plover_markdown_dictionary.py
plover_markdown_dictionary-0.2.0.dist-info/LICENSE
plover_markdown_dictionary-0.2.0.dist-info/METADATA
plover_markdown_dictionary-0.2.0.dist-info/WHEEL
plover_markdown_dictionary-0.2.0.dist-info/entry_points.txt
plover_markdown_dictionary-0.2.0.dist-info/top_level.txt
plover_markdown_dictionary-0.2.0.dist-info/zip-safe
plover_markdown_dictionary-0.2.0.dist-info/RECORD
