Metadata-Version: 2.1
Name: plover-markdown-dictionary
Version: 0.2.0
Summary: Markdown literate dictionary support for Plover
Home-page: https://github.com/antistic/plover_markdown_dictionary
Author: antistic
License: MIT
Keywords: plover plover_plugin
Platform: UNKNOWN
Classifier: Development Status :: 4 - Beta
Classifier: Environment :: Plugins
Classifier: Intended Audience :: End Users/Desktop
Classifier: License :: OSI Approved :: GNU General Public License v2 or later (GPLv2+)
Classifier: Operating System :: OS Independent
Classifier: Programming Language :: Python :: 3
Classifier: Programming Language :: Python :: 3.6
Classifier: Programming Language :: Python :: 3.7
Classifier: Programming Language :: Python :: 3.8
Classifier: Programming Language :: Python :: 3.9
Requires-Python: >=3.6
License-File: LICENSE
Requires-Dist: importlib-metadata
Requires-Dist: plover (>=4.0.0.dev10)
Provides-Extra: test
Requires-Dist: pytest ; extra == 'test'
